setup.py
pytorch_text_utils.egg-info/PKG-INFO
pytorch_text_utils.egg-info/SOURCES.txt
pytorch_text_utils.egg-info/dependency_links.txt
pytorch_text_utils.egg-info/requires.txt
pytorch_text_utils.egg-info/top_level.txt
torchtextutils/__init__.py
torchtextutils/common.py
torchtextutils/vocab.py
torchtextutils/data/__init__.py
torchtextutils/data/generator.py
torchtextutils/data/preprocessor/__init__.py
torchtextutils/data/preprocessor/batch.py
torchtextutils/data/preprocessor/noise.py
torchtextutils/iterator/__init__.py
torchtextutils/iterator/files.py
torchtextutils/iterator/sentences.py
torchtextutils/iterator/words.py