Metadata-Version: 1.1
Name: pytorch-text-utils
Version: 0.1.5
Summary: PyTorch Text Processing Utilities
Home-page: https://github.com/kaniblu/pytorch-text-utils
Author: Kang Min Yoo
Author-email: k@nib.lu
License: MIT
Keywords: pytorch text nlp utility
Platform: UNKNOWN
Classifier: Development Status :: 3 - Alpha
Classifier: Intended Audience :: Developers
Classifier: Programming Language :: Python :: 3
